EasyReflectometry/__init__.py
EasyReflectometry/data.py
EasyReflectometry/fitting.py
EasyReflectometry/main.py
EasyReflectometry/parameter_utils.py
EasyReflectometry/plot.py
EasyReflectometry/calculators/__init__.py
EasyReflectometry/calculators/calculator_base.py
EasyReflectometry/calculators/factory.py
EasyReflectometry/calculators/wrapper_base.py
EasyReflectometry/calculators/bornagain/calculator.py
EasyReflectometry/calculators/bornagain/wrapper.py
EasyReflectometry/calculators/refl1d/calculator.py
EasyReflectometry/calculators/refl1d/wrapper.py
EasyReflectometry/calculators/refnx/calculator.py
EasyReflectometry/calculators/refnx/wrapper.py
EasyReflectometry/experiment/__init__.py
EasyReflectometry/experiment/model.py
EasyReflectometry/experiment/model_collection.py
EasyReflectometry/experiment/resolution_functions.py
EasyReflectometry/measurement/data.py
EasyReflectometry/sample/__init__.py
EasyReflectometry/sample/base_core.py
EasyReflectometry/sample/base_element_collection.py
EasyReflectometry/sample/sample.py
EasyReflectometry/sample/assemblies/base_assembly.py
EasyReflectometry/sample/assemblies/gradient_layer.py
EasyReflectometry/sample/assemblies/multilayer.py
EasyReflectometry/sample/assemblies/repeating_multilayer.py
EasyReflectometry/sample/assemblies/surfactant_layer.py
EasyReflectometry/sample/elements/layers/layer.py
EasyReflectometry/sample/elements/layers/layer_area_per_molecule.py
EasyReflectometry/sample/elements/layers/layer_collection.py
EasyReflectometry/sample/elements/materials/material.py
EasyReflectometry/sample/elements/materials/material_collection.py
EasyReflectometry/sample/elements/materials/material_density.py
EasyReflectometry/sample/elements/materials/material_mixture.py
EasyReflectometry/sample/elements/materials/material_solvated.py
EasyReflectometry/special/calculations.py
EasyReflectometry/special/parsing.py
easyreflectometrylib-0.0.7.dist-info/METADATA
easyreflectometrylib-0.0.7.dist-info/WHEEL
easyreflectometrylib-0.0.7.dist-info/licenses/AUTHORS.rst
easyreflectometrylib-0.0.7.dist-info/licenses/LICENSE
easyreflectometrylib-0.0.7.dist-info/RECORD
